qpretrieve/__init__.py
qpretrieve/_ndarray_backend.py
qpretrieve/_version.py
qpretrieve/data_array_layout.py
qpretrieve/filter.py
qpretrieve/utils.py
qpretrieve/fourier/__init__.py
qpretrieve/fourier/base.py
qpretrieve/fourier/ff_cupy.py
qpretrieve/fourier/ff_numpy.py
qpretrieve/fourier/ff_pyfftw.py
qpretrieve/interfere/__init__.py
qpretrieve/interfere/base.py
qpretrieve/interfere/if_oah.py
qpretrieve/interfere/if_qlsi.py
qpretrieve-0.6.0.dist-info/licenses/LICENSE
qpretrieve-0.6.0.dist-info/METADATA
qpretrieve-0.6.0.dist-info/WHEEL
qpretrieve-0.6.0.dist-info/top_level.txt
qpretrieve-0.6.0.dist-info/RECORD
