Metadata-Version: 2.4
Name: qpretrieve
Version: 0.6.0
Summary: library for phase retrieval from holograms
Author-email: Paul Müller <dev@craban.de>, Eoghan O'Connell <eoclives@hotmail.com>
License: MIT
Project-URL: Repository, https://github.com/RI-imaging/qpretrieve
Project-URL: Documentation, https://qpretrieve.readthedocs.io/en/stable/
Project-URL: Changelog, https://github.com/RI-imaging/qpretrieve/blob/main/CHANGELOG
Keywords: digital holographic microscopy,optics,quantitative phase imaging,refractive index,numerical focusing,scattering
Classifier: Operating System :: OS Independent
Classifier: Programming Language :: Python :: 3
Classifier: Intended Audience :: Science/Research
Requires-Python: <4,>=3.10
License-File: LICENSE
Requires-Dist: numpy>=1.9.0
Requires-Dist: scikit-image>=0.11.0
Requires-Dist: scipy>=0.18.0
Provides-Extra: fftw
Requires-Dist: pyfftw>=0.12.0; extra == "fftw"
Provides-Extra: cupy
Requires-Dist: cupy-cuda12x; platform_system != "Darwin" and extra == "cupy"
Dynamic: license-file
